pytor/__init__.py
pytor/__main__.py
pytor/ed25519.py
pytor/onion.py
pytor/test/__init__.py
pytor/test/test_onions.py
pytor-0.1.9.dist-info/entry_points.txt
pytor-0.1.9.dist-info/WHEEL
pytor-0.1.9.dist-info/METADATA
pytor-0.1.9.dist-info/RECORD
